suger_sdk_python/__init__.py
suger_sdk_python/api_client.py
suger_sdk_python/api_response.py
suger_sdk_python/configuration.py
suger_sdk_python/exceptions.py
suger_sdk_python/py.typed
suger_sdk_python/rest.py
suger_sdk_python/api/__init__.py
suger_sdk_python/api/api_api.py
suger_sdk_python/api/billing_api.py
suger_sdk_python/api/buyer_api.py
suger_sdk_python/api/contact_api.py
suger_sdk_python/api/entitlement_api.py
suger_sdk_python/api/metering_api.py
suger_sdk_python/api/notification_api.py
suger_sdk_python/api/offer_api.py
suger_sdk_python/api/product_api.py
suger_sdk_python/api/report_api.py
suger_sdk_python/api/support_api.py
suger_sdk_python/models/__init__.py
suger_sdk_python/models/add_entitlement_credit_params.py
suger_sdk_python/models/add_entitlement_credit_response.py
suger_sdk_python/models/adyen_buyer.py
suger_sdk_python/models/aggregated_metering_usage_record.py
suger_sdk_python/models/alibaba_marketplace_product.py
suger_sdk_python/models/alibaba_marketplace_product_extra.py
suger_sdk_python/models/alibaba_marketplace_product_extras.py
suger_sdk_python/models/alibaba_marketplace_product_shop_info.py
suger_sdk_python/models/alibaba_marketplace_product_shop_info_telephones.py
suger_sdk_python/models/alibaba_marketplace_product_shop_info_wang_wang.py
suger_sdk_python/models/alibaba_marketplace_product_shop_info_wang_wangs.py
suger_sdk_python/models/alibaba_marketplace_product_sku.py
suger_sdk_python/models/alibaba_marketplace_product_sku_module.py
suger_sdk_python/models/alibaba_marketplace_product_sku_module_properties.py
suger_sdk_python/models/alibaba_marketplace_product_sku_module_property.py
suger_sdk_python/models/alibaba_marketplace_product_sku_module_property_value.py
suger_sdk_python/models/alibaba_marketplace_product_sku_module_property_values.py
suger_sdk_python/models/alibaba_marketplace_product_sku_modules.py
suger_sdk_python/models/alibaba_marketplace_product_sku_order_period.py
suger_sdk_python-3.128.221.dist-info/METADATA
suger_sdk_python-3.128.221.dist-info/WHEEL
suger_sdk_python-3.128.221.dist-info/top_level.txt
suger_sdk_python-3.128.221.dist-info/RECORD
