Metadata-Version: 2.1
Name: suger-sdk-python
Version: 3.128.221
Summary: Suger API
Home-page: 
Author: Suger Support
Author-email: support@suger.io
Keywords: OpenAPI,OpenAPI-Generator,Suger API
Requires-Dist: urllib3<3.0.0,>=2.1.0
Requires-Dist: python-dateutil>=2.8.2
Requires-Dist: pydantic>=2
Requires-Dist: typing-extensions>=4.7.1
